crypto_pandas_pro/main.py
crypto_pandas_pro-0.0.1.dist-info/METADATA
crypto_pandas_pro-0.0.1.dist-info/WHEEL
crypto_pandas_pro-0.0.1.dist-info/RECORD
