Metadata-Version: 2.3
Name: crypto-pandas-pro
Version: 0.0.1
Summary: Stub version of crypto-pandas-pro
Author: lucas
Author-email: lucasjamar@hotmail.com
Requires-Python: >=3.12
Classifier: Programming Language :: Python :: 3
Classifier: Programming Language :: Python :: 3.12
Classifier: Programming Language :: Python :: 3.13
